pyseqtender/__init__.py
pyseqtender/pyseqtender.py
pyseqtender-0.1.2.dist-info/METADATA
pyseqtender-0.1.2.dist-info/WHEEL
pyseqtender-0.1.2.dist-info/top_level.txt
pyseqtender-0.1.2.dist-info/RECORD
