Metadata-Version: 2.1
Name: pyseqtender
Version: 0.1.2
Summary: Distributed NGS pipelines made easy
Home-page: https://pyseqtender.biodatageeks.org
Author: biodatageeks
Author-email: team@biodatageeks.org
License: UNKNOWN
Platform: UNKNOWN
Classifier: Development Status :: 3 - Alpha
Classifier: Intended Audience :: Developers
Classifier: License :: OSI Approved :: Apache Software License
Classifier: Programming Language :: Python
Classifier: Programming Language :: Python :: 3
Classifier: Programming Language :: Python :: 3.7
Classifier: Programming Language :: Python :: Implementation :: CPython
Classifier: Programming Language :: Python :: Implementation :: PyPy
Requires-Dist: setuptools
Requires-Dist: typeguard (==2.5.0)
Requires-Dist: pyspark (==3.0.1)
Requires-Dist: findspark
Provides-Extra: rest
Requires-Dist: Sphinx ; extra == 'rest'
